AcmP/AdvCmnAPI_CM2.py
AcmP/AdvMotApi_CM2.py
AcmP/AdvMotDrv.py
AcmP/AdvMotErr_CM2.py
AcmP/AdvMotPropID_CM2.py
AcmP/MotionInfo.py
AcmP/__init__.py
AcmP/utils.py
AcmP-0.1.3.dist-info/METADATA
AcmP-0.1.3.dist-info/WHEEL
AcmP-0.1.3.dist-info/top_level.txt
AcmP-0.1.3.dist-info/RECORD
