Metadata-Version: 2.1
Name: AcmP
Version: 0.1.3
Summary: For developers of Advantech PCIE-12xx series access to the AdvMot API.
Home-page: https://github.com/Michelle-Tsai/ma-advmot2
Author: Advantech/MA
Author-email: michelle.tsai@advantech.com.tw
License: Apache License 2.0
Keywords: Advantech,PCIE-1203M,PCIE1203M,PCIE-1245,PCIE1245
